bff/__init__.py
bff/fancy.py
bff-0.1.2.dist-info/METADATA
bff-0.1.2.dist-info/WHEEL
bff-0.1.2.dist-info/top_level.txt
bff-0.1.2.dist-info/RECORD
