Metadata-Version: 2.1
Name: bff
Version: 0.1.2
Summary: Best Fancy Functions, your Best Friend Forever
Home-page: https://github.com/axelfahy/FancyThings/tree/master/bff
Author: Axel Fahy
Author-email: axel@fahy.net
License: MIT
Platform: UNKNOWN
Requires-Python: >=3.6
Requires-Dist: matplotlib (==3.0.3)
Requires-Dist: pandas (==0.24.2)
Requires-Dist: typing (==3.6.6)
